jassor/__init__.py
jassor/components/__init__.py
jassor/components/__init__.pyi
jassor/components/blind_mark.py
jassor/components/create_mask/__init__.py
jassor/components/create_mask/__init__.pyi
jassor/components/create_mask/area_diff.py
jassor/components/create_mask/back_free.py
jassor/components/create_mask/cross_entropy.py
jassor/components/create_mask/edge_diff.py
jassor/components/create_mask/edge_diff2.py
jassor/components/create_mask/modnet_predict.py
jassor/components/create_mask/pixel_diff.py
jassor/components/create_mask/pixel_diff_boge.py
jassor/components/data/__init__.py
jassor/components/data/__init__.pyi
jassor/components/data/cropper.py
jassor/components/data/interface.py
jassor/components/data/reader.py
jassor/components/data/reader_asap.py
jassor/components/data/reader_image.py
jassor/components/data/reader_numpy.py
jassor/components/data/reader_openslide.py
jassor/components/data/reader_tiff.py
jassor/components/data/single_predict_crop_dataset.py
jassor/components/data/slide_info.py
jassor/components/data/utils.py
jassor/components/paint/painter.py
jassor/shape/__init__.py
jassor/shape/interface.py
jassor/shape/shapely_impl/__init__.py
jassor/shape/shapely_impl/definition.py
jassor/shape/shapely_impl/functional.py
jassor/shape/shapely_impl/impl_base.py
jassor/shape/shapely_impl/impl_circle.py
jassor/shape/shapely_impl/impl_empty.py
jassor/shape/shapely_impl/impl_full.py
jassor/shape/shapely_impl/impl_multi_complex.py
jassor/shape/shapely_impl/impl_multi_simple.py
jassor/shape/shapely_impl/impl_region.py
jassor/shape/shapely_impl/impl_single_complex.py
jassor/shape/shapely_impl/impl_single_simple.py
jassor/shape/shapely_impl/polygon_creators.py
jassor/utils/__init__.py
jassor/utils/__init__.pyi
jassor/utils/align_in_fourier.py
jassor/utils/align_in_keypoint.py
jassor/utils/bbox.py
jassor/utils/color.py
jassor/utils/contour.py
jassor/utils/crop_det_label.py
jassor/utils/cropper.py
jassor/utils/ipynb2pycode.py
jassor/utils/iter_method.py
jassor-0.8.2.dist-info/licenses/LICENSE
jassor-0.8.2.dist-info/METADATA
jassor-0.8.2.dist-info/WHEEL
jassor-0.8.2.dist-info/top_level.txt
jassor-0.8.2.dist-info/RECORD
