Metadata-Version: 2.4
Name: jassor
Version: 0.8.2
Summary: utils of jassor
Author-email: jassor <lq.jassor@gmail.com>
License-Expression: MIT
Project-URL: project_source, https://github.com/name-used/jassor
Keywords: jassor,utils,shape,image
Classifier: Intended Audience :: Developers
Classifier: Operating System :: OS Independent
Classifier: Programming Language :: Python :: 3
Requires-Python: >=3.9
License-File: LICENSE
Requires-Dist: numpy
Requires-Dist: opencv-python
Requires-Dist: shapely
Requires-Dist: matplotlib
Requires-Dist: Pillow
Provides-Extra: dev
Requires-Dist: onnxruntime; extra == "dev"
Requires-Dist: scipy; extra == "dev"
Requires-Dist: skimage; extra == "dev"
Requires-Dist: PyQt5; extra == "dev"
Requires-Dist: openslide; extra == "dev"
Requires-Dist: tifffile; extra == "dev"
Requires-Dist: tiffslide; extra == "dev"
Dynamic: license-file
